aslabs/dependencies/flask/__init__.py
aslabs/dependencies/flask/flask.py
aslabs_dependencies_flask-0.0.2.dist-info/WHEEL
aslabs_dependencies_flask-0.0.2.dist-info/METADATA
aslabs_dependencies_flask-0.0.2.dist-info/RECORD
