Metadata-Version: 2.1
Name: aslabs-dependencies-flask
Version: 0.0.2
Summary: 
Author: Titusz Ban
Author-email: tituszban@antisociallabs.io
Requires-Python: >=3.9,<4.0
Classifier: Programming Language :: Python :: 3
Classifier: Programming Language :: Python :: 3.9
Classifier: Programming Language :: Python :: 3.10
Classifier: Programming Language :: Python :: 3.11
Requires-Dist: Flask (>=2.0.3,<3.0.0)
Requires-Dist: aslabs-dependencies
